confmodel/__init__.py
confmodel/_version.py
confmodel/config.py
confmodel/errors.py
confmodel/fallbacks.py
confmodel/fields.py
confmodel/interfaces.py
confmodel/tests/__init__.py
confmodel/tests/test_config.py
confmodel/tests/test_fallbacks.py
confmodel/tests/test_fields.py
confmodel-0.2.0.dist-info/DESCRIPTION.rst
confmodel-0.2.0.dist-info/METADATA
confmodel-0.2.0.dist-info/metadata.json
confmodel-0.2.0.dist-info/RECORD
confmodel-0.2.0.dist-info/top_level.txt
confmodel-0.2.0.dist-info/WHEEL
