Metadata-Version: 2.0
Name: confmodel
Version: 0.2.0
Summary: Declarative configuration access and validation system.
Home-page: http://github.com/praekelt/confmodel
Author: Praekelt Foundation
Author-email: dev@praekeltfoundation.org
License: BSD
Platform: UNKNOWN
Classifier: Development Status :: 4 - Beta
Classifier: Intended Audience :: Developers
Classifier: License :: OSI Approved :: BSD License
Classifier: Operating System :: POSIX
Classifier: Programming Language :: Python
Classifier: Topic :: Software Development :: Libraries :: Python Modules
Requires-Dist: zope.interface
